neuralink/__init__.py
neuralink/_version.py
neuralink/activation.py
neuralink/base.py
neuralink/cost.py
neuralink/initiation.py
neuralink/layer.py
neuralink/logger.py
neuralink/modelling.py
neuralink/optimization.py
neuralink/parameters.py
neuralink/prediction.py
neuralink/propagation.py
neuralink-0.0.1.dist-info/LICENSE
neuralink-0.0.1.dist-info/METADATA
neuralink-0.0.1.dist-info/WHEEL
neuralink-0.0.1.dist-info/top_level.txt
neuralink-0.0.1.dist-info/RECORD
