Metadata-Version: 2.1
Name: neuralink
Version: 0.0.1
Summary: This is a learning notes from deeplearning.AI at Coursera, which also provides basic DeepLearning tools.
Author: Chengran (Owen) Ouyang
Author-email: chengranouyang@gmail.com
License: Apache License
Keywords: Neuralink documentation tutorial
Platform: UNKNOWN
License-File: LICENSE
